jury/__init__.py
jury/cli.py
jury/collator.py
jury/core.py
jury/definitions.py
jury/tokenizer.py
jury/metrics/__init__.py
jury/metrics/_core/__init__.py
jury/metrics/_core/auto.py
jury/metrics/_core/auxiliary.py
jury/metrics/_core/base.py
jury/metrics/_core/utils.py
jury/metrics/accuracy/__init__.py
jury/metrics/accuracy/accuracy.py
jury/metrics/accuracy/accuracy_for_language_generation.py
jury/metrics/accuracy/accuracy_for_sequence_classification.py
jury/metrics/bartscore/__init__.py
jury/metrics/bartscore/bartscore.py
jury/metrics/bartscore/bartscore_for_language_generation.py
jury/metrics/bertscore/__init__.py
jury/metrics/bertscore/bertscore.py
jury/metrics/bertscore/bertscore_for_language_generation.py
jury/metrics/bleu/__init__.py
jury/metrics/bleu/bleu.py
jury/metrics/bleu/bleu_for_language_generation.py
jury/metrics/bleurt/__init__.py
jury/metrics/bleurt/bleurt.py
jury/metrics/bleurt/bleurt_for_language_generation.py
jury/metrics/cer/__init__.py
jury/metrics/cer/cer.py
jury/metrics/cer/cer_for_language_generation.py
jury/metrics/chrf/__init__.py
jury/metrics/chrf/chrf.py
jury/metrics/chrf/chrf_for_language_generation.py
jury/metrics/comet/__init__.py
jury/metrics/comet/comet.py
jury/metrics/comet/comet_for_language_generation.py
jury/metrics/f1/__init__.py
jury/metrics/f1/f1.py
jury/metrics/f1/f1_for_language_generation.py
jury/metrics/f1/f1_for_sequence_classification.py
jury/metrics/meteor/__init__.py
jury/metrics/meteor/meteor.py
jury/metrics/meteor/meteor_for_language_generation.py
jury/metrics/precision/__init__.py
jury/metrics/precision/precision.py
jury/metrics/precision/precision_for_language_generation.py
jury/metrics/precision/precision_for_sequence_classification.py
jury/metrics/prism/__init__.py
jury/metrics/prism/prism.py
jury/metrics/prism/prism_for_language_generation.py
jury/metrics/recall/__init__.py
jury/metrics/recall/recall.py
jury/metrics/recall/recall_for_language_generation.py
jury/metrics/recall/recall_for_sequence_classification.py
jury-2.3.1.dist-info/LICENSE
jury-2.3.1.dist-info/METADATA
jury-2.3.1.dist-info/WHEEL
jury-2.3.1.dist-info/entry_points.txt
jury-2.3.1.dist-info/top_level.txt
jury-2.3.1.dist-info/RECORD
