Metadata-Version: 2.1
Name: jury
Version: 2.3.1
Summary: Evaluation toolkit for neural language generation.
Home-page: https://github.com/obss/jury
Author: 
License: MIT
Keywords: machine-learning,deep-learning,ml,pytorch,NLP,evaluation,question-answering,question-generation
Classifier: Development Status :: 5 - Production/Stable
Classifier: Operating System :: OS Independent
Classifier: Intended Audience :: Developers
Classifier: Intended Audience :: Science/Research
Classifier: Programming Language :: Python :: 3
Classifier: Programming Language :: Python :: 3.8
Classifier: Programming Language :: Python :: 3.9
Classifier: Programming Language :: Python :: 3.10
Classifier: Programming Language :: Python :: 3.11
Classifier: Topic :: Software Development :: Libraries
Classifier: Topic :: Software Development :: Libraries :: Python Modules
Classifier: Topic :: Education
Classifier: Topic :: Scientific/Engineering
Classifier: Topic :: Scientific/Engineering :: Artificial Intelligence
Requires-Python: >=3.8
License-File: LICENSE
Requires-Dist: click ==8.0.4
Requires-Dist: evaluate <0.5,>=0.4
Requires-Dist: datasets <2.10,>=2.9
Requires-Dist: fire >=0.4.0
Requires-Dist: nltk <3.7.1,>=3.6.6
Requires-Dist: rouge-score ==0.0.4
Requires-Dist: scikit-learn
Requires-Dist: tqdm
Requires-Dist: validators
Provides-Extra: dev
Requires-Dist: black ==21.7b0 ; extra == 'dev'
Requires-Dist: deepdiff ==5.5.0 ; extra == 'dev'
Requires-Dist: flake8 ==3.9.2 ; extra == 'dev'
Requires-Dist: isort ==5.9.2 ; extra == 'dev'
Requires-Dist: pytest >=7.0.1 ; extra == 'dev'
Requires-Dist: pytest-cov >=3.0.0 ; extra == 'dev'
Requires-Dist: pytest-timeout >=2.1.0 ; extra == 'dev'
Requires-Dist: sacrebleu >=2.0.0 ; extra == 'dev'
Requires-Dist: bert-score ==0.3.11 ; extra == 'dev'
Requires-Dist: jiwer >=2.3.0 ; extra == 'dev'
Requires-Dist: seqeval ==1.2.2 ; extra == 'dev'
Requires-Dist: sentencepiece <0.2,>=0.1.99 ; extra == 'dev'
Requires-Dist: unbabel-comet ==2.0.1 ; extra == 'dev'
Requires-Dist: protobuf <3.21,>=3.20.3 ; extra == 'dev'
Requires-Dist: fairseq ==0.9.0 ; extra == 'dev'
Requires-Dist: numpy <1.24,>=1.23 ; extra == 'dev'
Provides-Extra: metrics
Requires-Dist: sacrebleu >=2.0.0 ; extra == 'metrics'
Requires-Dist: bert-score ==0.3.11 ; extra == 'metrics'
Requires-Dist: jiwer >=2.3.0 ; extra == 'metrics'
Requires-Dist: seqeval ==1.2.2 ; extra == 'metrics'
Requires-Dist: sentencepiece <0.2,>=0.1.99 ; extra == 'metrics'
Requires-Dist: unbabel-comet ==2.0.1 ; extra == 'metrics'
Requires-Dist: protobuf <3.21,>=3.20.3 ; extra == 'metrics'
Requires-Dist: fairseq ==0.9.0 ; extra == 'metrics'
Requires-Dist: numpy <1.24,>=1.23 ; extra == 'metrics'
Provides-Extra: prism
Requires-Dist: fairseq ==0.9.0 ; extra == 'prism'
Requires-Dist: numpy <1.24,>=1.23 ; extra == 'prism'
